{
  "project_info": {
    "project_number": "29842301804",
    "project_id": "perguntas-304217",
    "storage_bucket": "perguntas-304217.appspot.com"
  },
  "client": [
    {
      "client_info": {
        "mobilesdk_app_id": "1:29842301804:android:348b81ed5aca525ec84949",
        "android_client_info": {
          "package_name": "cc.tmvdl.pq"
        }
      },
      "oauth_client": [
        {
          "client_id": "29842301804-42rl0elevi4chctm8tti46uo70naan22.apps.googleusercontent.com",
          "client_type": 3
        }
      ],
      "api_key": [
        {
          "current_key": "AIzaSyBqS69tdueTCTsgUQ6faq_1pvw8Oi1pvQc"
        }
      ],
      "services": {
        "appinvite_service": {
          "other_platform_oauth_client": [
            {
              "client_id": "29842301804-42rl0elevi4chctm8tti46uo70naan22.apps.googleusercontent.com",
              "client_type": 3
            }
          ]
        }
      }
    }
  ],
  "configuration_version": "1"
}